{
  "date": "2026-07-12",
  "updated_at": "2026-07-12T06:42:39.231582+09:00",
  "new_counts": {
    "news": 1,
    "global_trends": 0,
    "policy": 0,
    "reports": 0,
    "academic_domestic": 3,
    "academic_international": 0
  },
  "sections": {
    "news": [
      {
        "title": "충북교육청, 생성형 AI '업무비서' 본격 가동...행정 혁신 박차",
        "url": "https://www.newstnt.com/news/articleView.html?idxno=709844",
        "source": "네이버뉴스",
        "author": "",
        "published_date": "2026-07-12",
        "summary": "충북교육청은 12일 생성형 AI와 검색증강생성(RAG) 기술을 활용한 업무지원 서비스 '업무비서'를 본청, 교육지원청, 직속기관 등 도내 행정기관에 도입했다. 이 서비스는 사용자가 자연어로 질문하면 방대한 업무 자료를 기반으로 답변을 제공하여 교육 행정의 효율성을 높이는 것을 목표로 한다. '업무비서' 가동을 통해 교육 기관의 행정 업무를 혁신하고, 행정 직원의 업무 부담을 경감하여 교육 본연의 역할에 집중할 수 있는 환경을 조성할 것으로 기대된다.",
        "score": 4.0,
        "implications": "[관련업무] AI·디지털 기반 교육혁신 운영, AI·디지털 활용 및 AI 융합교육\n[정책제언] 서울시교육청도 생성형 AI 기반의 교육행정 업무지원 시스템 'AI 업무비서' 도입을 검토해야 한다. 본청 및 교육지원청 등 행정기관의 반복적 질의응답, 문서작성 지원, 자료 검색 등에 AI를 활용하여 행정 효율을 극대화하고, 이를 통해 교직원이 학생 교육과 본연의 업무에 집중할 수 있도록 지원하는 정책을 추진해야 한다.\n[참고사항] 시스템 구축 시 서울시교육청의 방대한 내부 정책 및 규정 데이터를 학습시키기 위한 검색증강생성(RAG) 기술 적용을 고려하고, 데이터 보안 및 개인정보 보호 방안을 철저히 마련해야 한다. 또한, 도입 초기 교직원 대상의 충분한 활용 교육과 AI 답변에 대한 검증 프로세스 마련이 중요하다.",
        "collected_date": "2026-07-12",
        "is_new": true
      }
    ],
    "global_trends": [],
    "policy": [],
    "reports": [],
    "academic_domestic": [
      {
        "title": "대학 신입생의 전공탐색 경험에 기반한 생성형 인공지능 활용 지원 방안 탐색",
        "url": "https://doi.org/10.31041/jme.2026.11.2.141",
        "source": "Journal of Multiculture and Education",
        "author": ", Suyeon Lim, Sangsoo Lee",
        "published_date": "2026",
        "summary": "본 연구는 S대학교 신입생 10명을 대상으로 심층 면담을 통해 전공탐색 경험의 어려움을 분석하고, 생성형 인공지능(AI) 활용 지원 방안을 탐색하였다. 신입생들은 전공탐색 과정에서 정보 부족(8명), 진로 불확실성(7명), 개인적 흥미와 적성 파악의 어려움(6명) 등을 겪는 것으로 나타났다. 이에 대한 생성형 AI 기반의 지원 방안으로 개인 맞춤형 정보 제공, 진로 시뮬레이션, AI 튜터링을 통한 상담 지원 등이 제안되었으며, 특히 AI를 활용한 '전공 관련 최신 정보 요약 및 제공'에 대한 만족도가 높았다. 이는 생성형 AI가 학생들의 전공탐색 과정에서 실질적인 정보 접근성을 높이고 맞춤형 지원을 제공하여 진로 설계에 긍정적인 영향을 미칠 수 있음을 시사한다.",
        "score": 4.5,
        "implications": "[관련업무] 1. AI·디지털 기반 교육혁신 운영, 2. AI·디지털 활용 및 AI 융합교육, 4. AI·디지털 리터러시 교육 활성화\n[정책제언] 중·고등학생 및 대학 신입생을 대상으로 생성형 AI를 활용한 맞춤형 진로·전공 탐색 지원 시스템을 구축하고, AI 튜터링 및 정보 요약 서비스를 제공하는 프로그램을 개발해야 한다.\n[참고사항] 진로진학상담교사 및 학부모를 위한 생성형 AI 활용 가이드라인을 배포하여 학생들이 AI를 효과적으로 진로 탐색에 활용할 수 있도록 지도 역량을 강화하고, 윤리적 활용 교육을 병행한다.",
        "collected_date": "2026-07-12",
        "apa_citation": "Lim, S., Lee, S., Kim, E. (2026). 대학 신입생의 전공탐색 경험에 기반한 생성형 인공지능 활용 지원 방안 탐색. *Journal of Multiculture and Education*, 11(2). https://doi.org/10.31041/jme.2026.11.2.141",
        "identifier": "10.31041/jme.2026.11.2.141",
        "is_new": true
      },
      {
        "title": "유아 디지털 미디어 활용 교육 프로그램의 효과성 메타분석",
        "url": "https://doi.org/10.62783/shss.8.3.67",
        "source": "Studies on Humanities and Social Sciences",
        "author": "Jeongwan Go",
        "published_date": "2026",
        "summary": "본 연구는 2000년부터 2023년까지 국내 학술지에 게재된 유아 디지털 미디어 활용 교육 프로그램 관련 양적 연구 총 25편을 대상으로 메타분석을 수행하여 효과성을 종합적으로 분석하였다. 연구 결과, 유아 디지털 미디어 활용 교육 프로그램은 전반적으로 중간 수준 이상의 유의미한 효과 크기(d=.651)를 보였으며, 이는 유아의 인지, 사회·정서, 신체 발달에 긍정적인 영향을 미침을 시사한다. 특히, '언어/표현' 영역 중재 유형(d=1.03)과 '스마트 기기' 활용 유형(d=.81)에서 높은 효과 크기를 나타냈다. 또한, 프로그램 실시 기간이 10주 이상일 경우(d=.75) 단기 프로그램(1-4주, d=.54)보다 효과가 더욱 증대됨을 확인하여, 효과적인 유아 디지털 교육 프로그램 개발 및 장기적인 적용의 중요성을 강조한다.",
        "score": 4.5,
        "implications": "[관련업무] 1. AI·디지털 기반 교육혁신 운영, 2. AI·디지털 활용 및 AI 융합교육, 4. AI·디지털 리터러시 교육 활성화\n[정책제언] 유아 대상 디지털 미디어 활용 교육 프로그램 개발 시, 언어 및 표현력 증진에 중점을 둔 스마트 기기 활용 교육 콘텐츠를 적극적으로 포함하도록 권장하는 정책을 마련해야 한다.\n[참고사항] 프로그램 운영 시 최소 10주 이상의 중장기 운영을 통해 교육 효과를 극대화할 수 있도록 지원하며, 교재 및 놀이자료 개발 가이드라인에 언어/표현 영역 활동 예시를 강화한다.",
        "collected_date": "2026-07-12",
        "apa_citation": "Go, J. (2026). 유아 디지털 미디어 활용 교육 프로그램의 효과성 메타분석. *Studies on Humanities and Social Sciences*, 8(3). https://doi.org/10.62783/shss.8.3.67",
        "identifier": "10.62783/shss.8.3.67",
        "is_new": true
      },
      {
        "title": "유아교사의 디지털 리터리시가 디지털 놀이교수효능감에 미치는 영향",
        "url": "https://doi.org/10.62783/shss.8.3.5",
        "source": "Studies on Humanities and Social Sciences",
        "author": "Nawoon Park, Sangock Jang",
        "published_date": "2026",
        "summary": "본 연구는 경기도 유아교사 238명을 대상으로 설문조사를 실시하여 유아교사의 디지털 리터리시가 디지털 놀이교수효능감에 미치는 영향을 규명하였다. 분석 결과, 유아교사의 디지털 리터리시 하위 요인 중 '기술 활용 능력'(β=.45, p<.001)과 '사회-문화적 활용 능력'(β=.31, p<.001)이 디지털 놀이교수효능감에 정적인 영향을 미치는 것으로 나타났다. 특히, '기술 활용 능력'은 디지털 놀이교수효능감에 가장 큰 직접적인 영향을 미쳤으며, 이는 교사의 디지털 역량이 높을수록 디지털 환경에서의 놀이 지도에 대한 자신감이 향상됨을 의미한다. 연구는 유아교사의 효과적인 디지털 놀이 교육을 위해 기술 활용 및 디지털 시민성 교육 강화가 필수적임을 강조한다.",
        "score": 4.8,
        "implications": "[관련업무] 1. AI·디지털 기반 교육혁신 운영, 4. AI·디지털 리터러시 교육 활성화, 7. AI·디지털 기반 수업·평가혁신 전문가 연수, 9. AI·에듀테크 선도교사단 및 AIEDAP\n[정책제언] 유아 및 초등 교사 대상의 디지털 리터러시 역량 강화 연수 프로그램을 필수화하고, 특히 '기술 활용 능력'과 '사회-문화적 활용 능력'을 집중적으로 향상시킬 수 있는 내용으로 구성해야 한다.\n[참고사항] 연수 프로그램은 단순히 도구 사용법을 넘어, 디지털 기술을 활용한 놀이 중심 수업 설계 및 운영 방안, 그리고 AI 윤리 및 디지털 시민성 교육 내용을 포함하여 교사의 디지털 놀이교수효능감을 실질적으로 높일 수 있도록 구성한다.",
        "collected_date": "2026-07-12",
        "apa_citation": "Park, N., Jang, S. (2026). 유아교사의 디지털 리터리시가 디지털 놀이교수효능감에 미치는 영향. *Studies on Humanities and Social Sciences*, 8(3). https://doi.org/10.62783/shss.8.3.5",
        "identifier": "10.62783/shss.8.3.5",
        "is_new": true
      }
    ],
    "academic_international": []
  }
}