{
  "date": "2026-04-03",
  "updated_at": "2026-04-04T18:44:09.968288+09:00",
  "new_counts": {
    "news": 3,
    "global_trends": 0,
    "policy": 0,
    "reports": 0,
    "academic_domestic": 2,
    "academic_international": 2
  },
  "sections": {
    "news": [
      {
        "title": "[에듀플러스]태재대, 서울시 교육청과 AI 교육역량 강화 위한 업무협약...",
        "url": "https://www.etnews.com/20260403000146",
        "source": "전자신문",
        "author": "",
        "published_date": "2026-04-03",
        "summary": "대구보건대학교와 안동과학대학교는 기존 교육 체계에 AI와 디지털 기술을 결합하는 'AID 전환'을 공동 추진하며 AI 교육 협력에 나섰다. 양 대학은 이 협력을 통해 재학생뿐만 아니라 교직원, 지역 주민까지 포함하는 전방위적인 AI 교육 체계를 구축하고, 지역 전체의 AI 역량을 끌어올리겠다는 목표를 밝혔다. 이는 고등 교육기관 간의 협력을 통한 지역사회 AI 역량 강화의 중요한 사례이다.",
        "score": 4.5,
        "implications": "[관련업무] AI·디지털 기반 교육혁신 운영, AI·디지털 활용 및 AI 융합교육, AI·디지털 리터러시 교육 활성화, AI·디지털 기반 수업·평가혁신 전문가 연수\n[정책제언] 서울시교육청은 서울시 내 여러 고등 교육기관과의 다자간 협력 체계를 구축하여, 대구보건대와 안동과학대의 'AID 전환' 사례처럼 K-12 교육 현장 교원 및 학생, 나아가 학부모와 지역 주민을 포함하는 통합적인 AI·디지털 교육 프로그램을 공동으로 추진해야 한다.\n[참고사항] 지역 내 대학 및 연구기관과의 정기적인 협의체 구성, 다양한 교육 주체를 위한 맞춤형 AI 교육 콘텐츠 개발, 포괄적인 AI 리터러시 교육 확산을 위한 로드맵 수립.",
        "collected_date": "2026-04-03",
        "is_new": true
      },
      {
        "title": "증평군, AI 실증연구센터 기반 에듀테크 프로그램 본격 가동",
        "url": "https://www.thepublic.kr/news/articleView.html?idxno=299655",
        "source": "네이버뉴스",
        "author": "",
        "published_date": "2026-04-03",
        "summary": "충북 증평군이 지역 교육 혁신을 위해 이달부터 증평창의파크 내 AI 실증연구센터를 가동하며 에듀테크 기반 미래형 교육 생태계 조성에 박차를 가하고 있다. 군은 AI 실증연구센터에서 지역 학생과 주민을 대상으로 맞춤형 에듀테크 프로그램을 제공하여 AI 및 디지털 역량 강화를 지원하고 있다. 이는 지역사회 전반의 미래 교육 환경 구축을 목표로 하며, AI 활용 교육의 구체적인 현장 적용 사례를 제시한다.",
        "score": 4.5,
        "implications": "[관련업무] AI·디지털 기반 교육혁신 운영, AI·디지털 활용 및 AI 융합교육, AI·디지털 리터러시 교육 활성화\n[정책제언] 서울시교육청은 서울시 내 창의파크나 연구기관 등 지역 자원을 활용하여 '서울형 AI 실증 교육센터' 구축을 검토하고, K-12 학생 및 교사, 학부모, 나아가 서울시민을 대상으로 하는 AI·에듀테크 체험 및 리터러시 강화 프로그램을 개발 및 운영해야 한다.\n[참고사항] 지역 특성과 교육 수요를 반영한 AI 교육 콘텐츠 개발, 접근성 높은 공간 조성, 다양한 주체의 참여를 유도하는 홍보 및 운영 전략 마련.",
        "collected_date": "2026-04-03",
        "is_new": true
      },
      {
        "title": "증평군, 'AI 실증연구센터' 가동···에듀테크 기반 미래 교육 생태계 ...",
        "url": "http://www.enewstoday.co.kr/news/articleView.html?idxno=2414541",
        "source": "네이버뉴스",
        "author": "",
        "published_date": "2026-04-03",
        "summary": "태재대학교는 지난 8월 31일 서울시교육청과 '인공지능(AI) 교육역량 강화와 공교육 혁신 기반 마련'을 위한 업무협약을 체결했다. 양 기관은 이번 협약을 통해 AI 시대에 요구되는 새로운 교육 패러다임을 탐색하고, 보유한 지식과 자원을 상호 공유하며 AI 융합교육 및 AI 윤리 교육 관련 연구·교류 과제를 지속적으로 발굴하기로 했다. 이를 통해 공교육 체계가 기술 변화에 선제적으로 대응하도록 지원할 예정이다.",
        "score": 5.0,
        "implications": "[관련업무] AI·디지털 기반 교육혁신 운영, AI·디지털 활용 및 AI 융합교육, AI윤리·디지털 시민성 교육, AI·디지털 기반 수업·평가혁신 전문가 연수\n[정책제언] 태재대학교와의 업무협약을 기반으로 AI 융합교육 및 AI 윤리·디지털 시민성 교육 역량 강화를 위한 교원 연수 프로그램을 공동으로 설계하고 운영해야 한다. 특히, AI 시대 공교육이 나아가야 할 방향을 제시하는 연구 과제를 구체화하여 서울 공교육 현장에 적용 가능한 혁신 모델을 구축해야 한다.\n[참고사항] 대학의 전문성과 서울시교육청의 현장성을 결합한 실질적인 교원 연수 프로그램 개발, AI 융합교육의 성공 사례를 발굴하고 확산하기 위한 제도적 지원.",
        "collected_date": "2026-04-03",
        "is_new": true
      }
    ],
    "global_trends": [],
    "policy": [],
    "reports": [],
    "academic_domestic": [
      {
        "title": "유아 디지털 관련 현장지원자료 담론 분석:  텍스트마이닝을 중심으로",
        "url": "https://doi.org/10.22154/jcle.27.1.9",
        "source": "Korean Society of Children's Literature and Education",
        "author": ", Eun-Ju Kang, Seong-Hyun Kim",
        "published_date": "2026",
        "summary": "이 연구는 유아 디지털 교육과 관련된 현장지원자료의 담론 특성을 분석하고, 디지털 놀이 및 교육이 어떻게 의미 체계와 실천 논리 속에서 구성되는지 파악하는 것을 목적으로 한다. 2022 개정 유아교육과정에서 강조하는 디지털 역량 교육을 위한 자료를 분석하고자, 아이누리 포털에서 '디지털' 키워드를 포함하는 현장지원자료 27건을 수집하였다. 수집된 자료에서 '디지털'이 포함된 문단을 추출하여 빈도 분석, TF-IDF, 3어절 동시 출현어 분석, 의미망 군집 분석 등 다양한 텍스트마이닝 기법을 활용하여 분석하였다. 분석 결과, “디지털 미디어,” “놀이,” “교사,” “디지털 기기” 등의 용어가 높은 빈도로 나타나 디지털 도구를 활용한 놀이 중심 교수학습이 주요한 접근 방식임을 확인했다.",
        "score": 4.5,
        "implications": "[관련업무] AI·디지털 기반 교육혁신 운영, AI·디지털 리터러시 교육 활성화, AI·디지털 기반 수업·평가혁신 전문가 연수\n[정책제언] 유아 및 초등 저학년을 위한 디지털 교육 현장지원자료 개발 시, '놀이 중심' 학습과 '디지털 미디어 및 기기' 활용을 넘어 AI 윤리 및 디지털 시민성 요소를 강화하고 교사의 디지털 역량 증진을 위한 구체적인 가이드라인과 연수 프로그램을 제공해야 한다.\n[참고사항] 현장 교사들이 디지털 교육 자료를 쉽게 활용할 수 있도록 실제적인 교수 학습 사례와 함께 AI 윤리, 디지털 시민성, 미디어 리터러시 등의 내용을 통합하여 제공하고, 교사 연수 시 텍스트마이닝 결과로 나타난 주요 키워드와 관련된 실질적인 교수법을 다루는 것이 효과적이다.",
        "collected_date": "2026-04-03",
        "apa_citation": "Kang, E., Kim, S. (2026). 유아 디지털 관련 현장지원자료 담론 분석:  텍스트마이닝을 중심으로. *Korean Society of Children's Literature and Education*, 27(1). https://doi.org/10.22154/jcle.27.1.9",
        "identifier": "10.22154/jcle.27.1.9",
        "is_new": true
      },
      {
        "title": "인공지능 시대 전문 번역 교과 개편 사례 연구",
        "url": "https://doi.org/10.36747/ellf.91.3",
        "source": "Societe Coreenne d＇Enseignement de Langue et Litterature Francaises",
        "author": "Jeong-yeon Kim",
        "published_date": "2026",
        "summary": "이 연구는 인공지능(AI) 시대 도래에 따른 전문 번역 교육의 변화 필요성을 인식하고, 기존 교과과정 개편의 구체적 사례를 분석하는 것을 목적으로 한다. AI 기술 발전이 전문 번역 분야에 미치는 영향을 고찰하며, 번역사의 역할이 AI 도구 활용 및 AI 윤리 인지 등으로 확장됨에 따라 교육 현장의 대응 방안을 모색한다. 비록 구체적인 수치나 방법론은 명시되지 않았으나, AI 시대의 교육과정 혁신 방향을 제시함으로써 교육 체계가 새로운 기술 환경에 적응하는 방안에 대한 실질적인 통찰을 제공한다. 이는 AI와 융합된 전문 교육의 필요성을 강조하며, 고등 교육 기관의 교과 과정 설계에 중요한 시사점을 제공할 것으로 보인다.",
        "score": 4.5,
        "implications": "[관련업무] AI·디지털 활용 및 AI 융합교육, AI·정보(AI·SW) 교육, AI·디지털 리터러시 교육 활성화, AI·디지털 기반 수업·평가혁신 전문가 연수\n[정책제언] AI 시대에 필요한 핵심 역량을 중심으로 고등학교 특성화 및 마이스터고, 일반고 직업교육 과정의 교과 개편 가이드라인을 마련하고, AI 융합 분야별 교과 콘텐츠 개발 및 보급을 추진해야 한다.\n[참고사항] AI 도구 활용 능력, AI 윤리, 데이터 리터러시 등 미래 사회에 필수적인 역량을 각 교과 및 진로 분야에 맞춤형으로 통합하는 방안을 강구하고, 관련 교육 전문가 연수를 강화하여 교사의 AI 융합 교육 역량을 제고해야 한다.",
        "collected_date": "2026-04-03",
        "apa_citation": "Kim, J. (2026). 인공지능 시대 전문 번역 교과 개편 사례 연구. *Societe Coreenne d＇Enseignement de Langue et Litterature Francaises*, 91(0). https://doi.org/10.36747/ellf.91.3",
        "identifier": "10.36747/ellf.91.3",
        "is_new": true
      }
    ],
    "academic_international": [
      {
        "title": "Integrating Ethics and Career Futures with Technical Learning to Promote AI Literacy for Middle School Students: An Exploratory Study",
        "url": "https://eric.ed.gov/?id=EJ1387327",
        "source": "",
        "author": "Zhang, Helen, Lee, Irene, Ali, Safinah",
        "published_date": "2023",
        "summary": "이 탐색적 연구는 K-12 AI 교육의 필요성을 바탕으로, 중학생을 대상으로 AI 리터러시를 증진하기 위해 AI 기술 개념 학습과 더불어 윤리적/사회적 함의 및 AI 시대의 직업 미래를 통합한 'DAILy 워크숍'의 설계와 구현을 탐구했다. 워크숍은 학생들이 AI를 사회기술적 시스템으로 이해하고 그 윤리적, 정치적 함의를 인지하도록 돕는 데 초점을 맞췄다. 연구 결과, 워크숍 참여 후 대부분의 학생들이 AI의 기술적 측면뿐만 아니라 윤리적 고려 사항 및 미래 직업과의 연관성에 대한 이해를 향상시킨 것으로 나타났다. 이는 AI 교육이 단순히 기술 습득을 넘어선 종합적인 접근이 효과적임을 시사한다.",
        "score": 5,
        "implications": "[관련업무] AI·디지털 활용 및 AI 융합교육, AI·정보(AI·SW) 교육, AI윤리·디지털 시민성 교육, AI·디지털 기반 수업·평가혁신 전문가 연수\n[정책제언] 중학생을 포함한 K-12 AI 교육과정을 설계할 때, AI 기술 및 원리 학습과 함께 AI 윤리, 사회적 영향, 그리고 AI 시대의 직업 탐색 및 미래 설계 역량을 통합적으로 포함하는 교육 모델(예: DAILy 워크숍)을 개발하고 확대 적용해야 한다.\n[참고사항] AI 윤리 교육을 강화하기 위해 특정 교과(예: 정보, 사회)에만 국한하지 않고 AI 융합 교육의 일환으로 전 교과에서 다루어질 수 있도록 교재 개발 및 교사 연수를 지원하며, 다양한 진로 탐색 프로그램을 연계하는 방안을 모색해야 한다.",
        "collected_date": "2026-04-03",
        "apa_citation": "Zhang, Helen, Lee, Irene, Ali, Safinah, DiPaola, Daniella, Cheng, Yihong, Breazeal, Cynthia (2023). Integrating Ethics and Career Futures with Technical Learning to Promote AI Literacy for Middle School Students: An Exploratory Study. https://eric.ed.gov/?id=EJ1387327",
        "identifier": "EJ1387327",
        "is_new": true
      },
      {
        "title": "A Scoping Review of Empirical Research on AI Literacy Assessments",
        "url": "https://eric.ed.gov/?id=EJ1497456",
        "source": "",
        "author": "Jiahong Su, Xinyu Chen, Samuel Kai Wah Chu",
        "published_date": "2025",
        "summary": "이 범위 검토 연구는 2019년부터 2024년까지 발표된 36개의 AI 리터러시 평가 관련 경험적 연구를 분석하여 AI 리터러시가 어떻게 평가되어 왔는지 이해하고 향후 평가 개발을 위한 방향을 제시하는 것을 목적으로 한다. 연구는 평가 도구, 형식, 신뢰도 및 타당도 증거를 종합하며, AI 리터러시 평가를 위한 네 가지 핵심 측면(AI 지식, AI 윤리, AI에 대한 태도, AI 활용)을 제안했다. 핵심 발견은 대부분의 기존 연구가 주로 AI 지식 평가에 집중되었음을 보여주며, 이는 AI 윤리, 태도, 활용 등 다차원적 요소들을 통합한 평가 개발의 필요성을 강조한다. 이 결과는 K-12 학생들의 포괄적인 AI 리터러시 함양을 위한 평가 설계에 중요한 시사점을 제공한다.",
        "score": 5,
        "implications": "[관련업무] AI·디지털 리터러시 교육 활성화, AI·정보(AI·SW) 교육, AI윤리·디지털 시민성 교육, AI·디지털 기반 교육혁신 운영\n[정책제언] K-12 학생들의 AI 리터러시 함양을 위한 교육과정 및 평가 기준을 마련할 때, 단순히 AI 기술 지식 습득을 넘어 AI 윤리, AI에 대한 긍정적 태도 형성, 그리고 실생활에서의 AI 활용 능력을 종합적으로 평가할 수 있는 다차원적 평가 도구 개발 및 적용을 추진해야 한다.\n[참고사항] 교육 현장에서 AI 윤리, 태도, 활용 능력을 평가하기 위한 구체적인 루브릭 또는 평가 지표를 개발하고, 이를 교사 연수를 통해 확산하여 현장 교사들이 실질적으로 활용할 수 있도록 지원하는 것이 중요하다.",
        "collected_date": "2026-04-03",
        "apa_citation": "Jiahong Su, Xinyu Chen, Samuel Kai Wah Chu, Xiao Hu (2025). A Scoping Review of Empirical Research on AI Literacy Assessments. https://eric.ed.gov/?id=EJ1497456",
        "identifier": "EJ1497456",
        "is_new": true
      }
    ]
  }
}